{"autodetected":{},"short_doc":"Used to detect if the current browser supports a certain feature, and the type of the current browser. ...","aliases":{},"files":[{"linenr":328,"filename":"/Users/yshibukawa/personal/senchatouch/touch-2.3.0/src/env/OS.js"}],"tagname":"class","members":[],"alternateClassNames":[],"doc":"<p>Used to detect if the current browser supports a certain feature, and the type of the current browser.</p>\n","name":"Ext.is","id":"class-Ext.is","deprecated":{"text":"<p>Please refer to the <a href=\"#!/api/Ext.browser\" rel=\"Ext.browser\" class=\"docClass\">Ext.browser</a>, <a href=\"#!/api/Ext.os\" rel=\"Ext.os\" class=\"docClass\">Ext.os</a> and <a href=\"#!/api/Ext.feature\" rel=\"Ext.feature\" class=\"docClass\">Ext.feature</a> classes instead.</p>\n","version":"2.0.0"}}